creduse/__init__.py
creduse/__version__.py
creduse/_client.py
creduse/_exceptions.py
creduse/_httpclient.py
creduse/models/__init__.py
creduse/models/request_options.py
creduse/models/response_models.py
creduse-0.1.10.dist-info/METADATA
creduse-0.1.10.dist-info/WHEEL
creduse-0.1.10.dist-info/RECORD
