Metadata-Version: 2.4
Name: creduse
Version: 0.1.10
Summary: Python SDK for Creduse
Author-email: Creduse <support@creduse.com>
License: MIT License
Requires-Python: >=3.13
Requires-Dist: httpx>=0.28.1
Requires-Dist: pydantic>=2.10.6
